talqual/__init__.py
talqual/__main__.py
talqual/batch.py
talqual/cli.py
talqual/data.py
talqual/importer.py
talqual/main.py
talqual/templates.py
talqual/translation.py
talqual/views.py
talqual/zpt.py
talqual/parsers/__init__.py
talqual/parsers/html.py
talqual/static/__init__.py
talqual/static/org.transcrypt.__runtime__.js
talqual/static/scripts.js
talqual-0.0.4.dist-info/LICENSE
talqual-0.0.4.dist-info/METADATA
talqual-0.0.4.dist-info/WHEEL
talqual-0.0.4.dist-info/entry_points.txt
talqual-0.0.4.dist-info/top_level.txt
talqual-0.0.4.dist-info/RECORD
