Metadata-Version: 2.1
Name: talqual
Version: 0.0.4
Summary: TAL Chameleon (static site generator)
Home-page: https://gitlab.com/timbaler/talqual/
Author: Aleix Llusà Serra
Author-email: timbaler@timbaler.cat
License: GPLv3+
Project-URL: Documentation, https://gitlab.com/timbaler/talqual/
Project-URL: Source, https://gitlab.com/timbaler/talqual/
Project-URL: Tracker, https://gitlab.com/timbaler/talqual/issues
Classifier: License :: OSI Approved :: GNU General Public License v3 or later (GPLv3+)
Classifier: Intended Audience :: Developers
Classifier: Programming Language :: Python
Classifier: Programming Language :: Python :: 3
Classifier: Programming Language :: Python :: 3.9
Classifier: Programming Language :: Python :: 3.10
Classifier: Programming Language :: Python :: 3.11
Classifier: Development Status :: 3 - Alpha
Classifier: Topic :: Internet :: WWW/HTTP
Requires-Python: >=3.9
License-File: LICENSE
Requires-Dist: anytree
Requires-Dist: chameleon
Requires-Dist: click
Requires-Dist: docutils
Requires-Dist: pyyaml
Requires-Dist: importlib-metadata (~=1.0) ; python_version < "3.8"
Provides-Extra: multilingual
Requires-Dist: babel ; extra == 'multilingual'
Requires-Dist: babel-lingua-chameleon ; extra == 'multilingual'
Provides-Extra: test
Requires-Dist: sphinx ; extra == 'test'
Requires-Dist: pytest ; extra == 'test'
Requires-Dist: pytest-html ; extra == 'test'
Requires-Dist: pytest-cov ; extra == 'test'
Requires-Dist: coverage-conditional-plugin ; extra == 'test'
Requires-Dist: pytest-flake8 ; extra == 'test'
Requires-Dist: flake8 (<4) ; extra == 'test'
Requires-Dist: pytest-mock ; extra == 'test'
Requires-Dist: pytest-selenium ; extra == 'test'
Requires-Dist: flake8-isort ; extra == 'test'
Requires-Dist: transcrypt ; extra == 'test'
